{
  "kind": "collectionType",
  "collectionName": "events",
  "info": {
    "singularName": "event",
    "pluralName": "events",
    "displayName": "Event",
    "description": ""
  },
  "options": {
    "draftAndPublish": true
  },
  "pluginOptions": {
    "i18n": {
      "localized": true
    }
  },
  "attributes": {
    "event_start": {
      "type": "datetime",
      "pluginOptions": {
        "i18n": {
          "localized": true
        }
      },
      "required": true
    },
    "event_end": {
      "type": "datetime",
      "pluginOptions": {
        "i18n": {
          "localized": true
        }
      }
    },
    "include_time": {
      "type": "boolean",
      "pluginOptions": {
        "i18n": {
          "localized": true
        }
      },
      "default": true
    },
    "title": {
      "type": "string",
      "pluginOptions": {
        "i18n": {
          "localized": true
        }
      },
      "required": true
    },
    "shortDescription": {
      "type": "string",
      "pluginOptions": {
        "i18n": {
          "localized": true
        }
      }
    },
    "include_day": {
      "type": "boolean",
      "pluginOptions": {
        "i18n": {
          "localized": true
        }
      },
      "default": true
    },
    "location": {
      "type": "richtext",
      "pluginOptions": {
        "i18n": {
          "localized": true
        }
      }
    }
  }
}
